pycrossva/__init__.py
pycrossva/configuration.py
pycrossva/mappings.py
pycrossva/transform.py
pycrossva/utils.py
pycrossva/validation.py
pycrossva/resources/mapping_configuration_files/2012WHO_to_InSilicoVA.csv
pycrossva/resources/mapping_configuration_files/2012WHO_to_InSilicoVA_2012.csv
pycrossva/resources/mapping_configuration_files/2012WHO_to_InterVA4.csv
pycrossva/resources/mapping_configuration_files/2012WHO_to_InterVA5.csv
pycrossva/resources/mapping_configuration_files/2016WHOv141_to_InSilicoVA.csv
pycrossva/resources/mapping_configuration_files/2016WHOv141_to_InSilicoVA_2012.csv
pycrossva/resources/mapping_configuration_files/2016WHOv141_to_InterVA4.csv
pycrossva/resources/mapping_configuration_files/2016WHOv141_to_InterVA5.csv
pycrossva/resources/mapping_configuration_files/2016WHOv151_to_InSilicoVA.csv
pycrossva/resources/mapping_configuration_files/2016WHOv151_to_InSilicoVA_2012.csv
pycrossva/resources/mapping_configuration_files/2016WHOv151_to_InterVA4.csv
pycrossva/resources/mapping_configuration_files/2016WHOv151_to_InterVA5.csv
pycrossva/resources/mapping_configuration_files/2021WHO_to_InSilicoVA.csv
pycrossva/resources/mapping_configuration_files/2021WHO_to_InterVA5.csv
pycrossva/resources/mapping_configuration_files/PHMRCShort_to_InSilicoVA.csv
pycrossva/resources/mapping_configuration_files/PHMRCShort_to_InterVA5.csv
pycrossva/resources/mapping_configuration_files/example_config_1.csv
pycrossva/resources/mapping_configuration_files/example_config_2.csv
pycrossva/resources/sample_data/2012WHO_mock_data_1.csv
pycrossva/resources/sample_data/2016WHO_bad_data_1.csv
pycrossva/resources/sample_data/2016WHO_mock_data_1.csv
pycrossva/resources/sample_data/2016WHO_mock_data_2.csv
pycrossva/resources/sample_data/Mock_PHRMC_Data.csv
pycrossva/resources/sample_data/PHMRC_mock_data_1.csv
pycrossva/resources/sample_data/mock_data_2.csv
pycrossva/resources/sample_data/mock_data_2016WHO151.csv
pycrossva/resources/sample_data/test_data1.csv
pycrossva-0.98.dist-info/LICENSE
pycrossva-0.98.dist-info/METADATA
pycrossva-0.98.dist-info/WHEEL
pycrossva-0.98.dist-info/entry_points.txt
pycrossva-0.98.dist-info/top_level.txt
pycrossva-0.98.dist-info/RECORD
