Metadata-Version: 2.1
Name: pycrossva
Version: 0.98
Summary: Prepare data from WHO and PHRMC instruments for verbal autopsy algorithms
Author: ekarpinskiMITRE, pkmitre, owentrigueros, Peter Choi, Yue Chu, Jason Thomas
Maintainer-email: openVA Team <help@openva.net>
Project-URL: Homepage, https://github.com/verbal-autopsy-software/pyCrossVA
Project-URL: Bug Tracker, https://github.com/verbal-autopsy-software/pyCrossVA/issues
Keywords: verbal autopsy,data preparation
Classifier: Programming Language :: Python :: 3
Classifier: Programming Language :: Python :: 3.8
Classifier: Programming Language :: Python :: 3.9
Classifier: Programming Language :: Python :: 3.10
Classifier: Programming Language :: Python :: 3.11
Classifier: Programming Language :: Python :: 3.12
Classifier: License :: OSI Approved :: GNU General Public License v3 (GPLv3)
Classifier: Operating System :: OS Independent
Requires-Python: >=3.8
License-File: LICENSE
Requires-Dist: numpy>=1.22.0
Requires-Dist: pandas
Requires-Dist: Click
